{
  "slug": "index",
  "title": "Home",
  "items": [
    {
      "id": "2cfce991-9e2d-4e38-96de-de9f708f6d59",
      "type": "text",
      "content": "charlotte beltzung",
      "x": 240,
      "y": 96,
      "width": 624,
      "style": {
        "fontWeight": 400,
        "color": "#c7fcfe",
        "fontSize": 55
      }
    },
    {
      "id": "745afadb-0566-4f76-8ca8-e0eec0679df7",
      "type": "text",
      "content": "⎠ shop ⎝",
      "x": 640,
      "y": 168,
      "width": 80,
      "style": {
        "fontSize": 20
      }
    },
    {
      "id": "ac7fbeaa-ce84-4cc2-b0da-001e57c50001",
      "type": "text",
      "content": "⎠ ･◡･ ⎝",
      "x": 544,
      "y": 168,
      "width": 72,
      "style": {
        "fontSize": 20
      }
    },
    {
      "id": "772bcdea-447b-4ffe-bf41-00d6d46cdddc",
      "type": "text",
      "content": "⎠ textes ⎝",
      "x": 432,
      "y": 168,
      "width": 96,
      "style": {
        "fontSize": 20
      }
    },
    {
      "id": "ddbe6708-f2ee-4a0d-8244-897e764ec7b5",
      "type": "text",
      "content": "⎠ cv ⎝",
      "x": 352,
      "y": 168,
      "width": 56,
      "style": {
        "fontSize": 20
      }
    },
    {
      "id": "b93ff44a-33c0-479b-9b1e-a15dd2b14f9c",
      "type": "text",
      "content": "⎠ infos ⎝",
      "x": 248,
      "y": 168,
      "width": 88,
      "style": {
        "fontSize": 20
      }
    },
    {
      "id": "c559bb3c-1102-4b9a-ac41-a087baf4dfb1",
      "type": "image",
      "src": "assets/images/9d6dbead32c52e07.gif",
      "x": 16,
      "y": 720,
      "width": 181,
      "aspectRatio": 0.8829268292682927,
      "hoverSrc": "assets/images/0d7e5f2da2beaaf6.gif",
      "link": null
    },
    {
      "id": "305d932a-0a5e-439e-b826-c49a116b7b3f",
      "type": "text",
      "content": "Charlotte Beltzung © 2015-2026<br>Typo : <i>Degheest</i> by Ange Degheest, Camille Depalle, Eugénie Bidaut, Luna Delabre, Mandy Elbé, May Jolivet, Oriane Charvieux, Benjamin Gomez, Justine Herbel. Distributed by velvetyne.fr.<br>Développement du site : Gu",
      "x": 0,
      "y": 1104,
      "width": 1080,
      "style": {
        "fontFamily": "Director Regular",
        "fontSize": 10,
        "textAlign": "center"
      }
    }
  ],
  "style": {
    "colors": {
      "text": "#0432ff"
    },
    "typography": {
      "fontSize": 50,
      "fontFamily": "Director Regular"
    }
  }
}